cryptbuddy/__init__.py
cryptbuddy/commands/__init__.py
cryptbuddy/commands/encryption.py
cryptbuddy/commands/keychain.py
cryptbuddy/commands/misc.py
cryptbuddy/config.py
cryptbuddy/constants.py
cryptbuddy/functions/__init__.py
cryptbuddy/functions/asymmetric.py
cryptbuddy/functions/file_ops.py
cryptbuddy/functions/symmetric.py
cryptbuddy/main.py
cryptbuddy/operations/__init__.py
cryptbuddy/operations/asymmetric.py
cryptbuddy/operations/clean.py
cryptbuddy/operations/initialize.py
cryptbuddy/operations/logger.py
cryptbuddy/operations/symmetric.py
cryptbuddy/structs/__init__.py
cryptbuddy/structs/app_keys.py
cryptbuddy/structs/exceptions.py
cryptbuddy/structs/keychain.py
cryptbuddy/structs/options.py
cryptbuddy-1.0.2.dist-info/METADATA
cryptbuddy-1.0.2.dist-info/WHEEL
cryptbuddy-1.0.2.dist-info/entry_points.txt
cryptbuddy-1.0.2.dist-info/RECORD
