Metadata-Version: 2.1
Name: cryptbuddy
Version: 1.0.2
Summary: An over-engineered multithreaded file encryption CLI program
Author: Kush Patel
Author-email: kush@kush.in
Requires-Python: >=3.9,<4.0
Classifier: Programming Language :: Python :: 3
Classifier: Programming Language :: Python :: 3.9
Classifier: Programming Language :: Python :: 3.10
Classifier: Programming Language :: Python :: 3.11
Requires-Dist: PyNaCl (>=1.5.0,<2.0.0)
Requires-Dist: appdirs (>=1.4.4,<2.0.0)
Requires-Dist: msgpack (>=1.0.7,<2.0.0)
Requires-Dist: password-strength (>=0.0.3.post2,<0.0.4)
Requires-Dist: pytest (>=7.3.1,<8.0.0)
Requires-Dist: typer[all] (>=0.9.0,<0.10.0)
